{
  "fio version" : "fio-3.13",
  "timestamp" : 1580905036,
  "timestamp_ms" : 1580905036160,
  "time" : "Wed Feb  5 12:17:16 2020",
  "jobs" : [
    {
      "jobname" : "rand-read-128k",
      "groupid" : 0,
      "error" : 0,
      "eta" : 0,
      "elapsed" : 31,
      "job options" : {
        "runtime" : "30",
        "bs" : "128k",
        "rw" : "randread",
        "direct" : "1",
        "randrepeat" : "0",
        "ioengine" : "libaio",
        "iodepth" : "32",
        "filename" : "/dev/vdb"
      },
      "read" : {
        "io_bytes" : 53249441792,
        "io_kbytes" : 52001408,
        "bw_bytes" : 1774803912,
        "bw" : 1733206,
        "iops" : 13540.679265,
        "runtime" : 30003,
        "total_ios" : 406261,
        "short_ios" : 0,
        "drop_ios" : 0,
        "slat_ns" : {
          "min" : 3743,
          "max" : 492096,
          "mean" : 6771.308656,
          "stddev" : 2218.791965
        },
        "clat_ns" : {
          "min" : 115049,
          "max" : 11395602,
          "mean" : 2354171.764723,
          "stddev" : 257114.061419,
          "percentile" : {
            "1.000000" : 1630208,
            "5.000000" : 1810432,
            "10.000000" : 1941504,
            "20.000000" : 2244608,
            "30.000000" : 2342912,
            "40.000000" : 2375680,
            "50.000000" : 2408448,
            "60.000000" : 2441216,
            "70.000000" : 2473984,
            "80.000000" : 2506752,
            "90.000000" : 2572288,
            "95.000000" : 2637824,
            "99.000000" : 2736128,
            "99.500000" : 2768896,
            "99.900000" : 2867200,
            "99.950000" : 2932736,
            "99.990000" : 7700480
          }
        },
        "lat_ns" : {
          "min" : 119644,
          "max" : 11404300,
          "mean" : 2361368.930038,
          "stddev" : 257085.927277
        },
        "bw_min" : 1664512,
        "bw_max" : 2140416,
        "bw_agg" : 99.995116,
        "bw_mean" : 1733121.350000,
        "bw_dev" : 159144.561301,
        "bw_samples" : 60,
        "iops_min" : 13004,
        "iops_max" : 16722,
        "iops_mean" : 13539.983333,
        "iops_stddev" : 1243.294755,
        "iops_samples" : 60
      },
      "write" : {
        "io_bytes" : 0,
        "io_kbytes" : 0,
        "bw_bytes" : 0,
        "bw" : 0,
        "iops" : 0.000000,
        "runtime" : 0,
        "total_ios" : 0,
        "short_ios" : 0,
        "drop_ios" : 0,
        "slat_ns" : {
          "min" : 0,
          "max" : 0,
          "mean" : 0.000000,
          "stddev" : 0.000000
        },
        "clat_ns" : {
          "min" : 0,
          "max" : 0,
          "mean" : 0.000000,
          "stddev" : 0.000000,
          "percentile" : {
            "1.000000" : 0,
            "5.000000" : 0,
            "10.000000" : 0,
            "20.000000" : 0,
            "30.000000" : 0,
            "40.000000" : 0,
            "50.000000" : 0,
            "60.000000" : 0,
            "70.000000" : 0,
            "80.000000" : 0,
            "90.000000" : 0,
            "95.000000" : 0,
            "99.000000" : 0,
            "99.500000" : 0,
            "99.900000" : 0,
            "99.950000" : 0,
            "99.990000" : 0
          }
        },
        "lat_ns" : {
          "min" : 0,
          "max" : 0,
          "mean" : 0.000000,
          "stddev" : 0.000000
        },
        "bw_min" : 0,
        "bw_max" : 0,
        "bw_agg" : 0.000000,
        "bw_mean" : 0.000000,
        "bw_dev" : 0.000000,
        "bw_samples" : 0,
        "iops_min" : 0,
        "iops_max" : 0,
        "iops_mean" : 0.000000,
        "iops_stddev" : 0.000000,
        "iops_samples" : 0
      },
      "trim" : {
        "io_bytes" : 0,
        "io_kbytes" : 0,
        "bw_bytes" : 0,
        "bw" : 0,
        "iops" : 0.000000,
        "runtime" : 0,
        "total_ios" : 0,
        "short_ios" : 0,
        "drop_ios" : 0,
        "slat_ns" : {
          "min" : 0,
          "max" : 0,
          "mean" : 0.000000,
          "stddev" : 0.000000
        },
        "clat_ns" : {
          "min" : 0,
          "max" : 0,
          "mean" : 0.000000,
          "stddev" : 0.000000,
          "percentile" : {
            "1.000000" : 0,
            "5.000000" : 0,
            "10.000000" : 0,
            "20.000000" : 0,
            "30.000000" : 0,
            "40.000000" : 0,
            "50.000000" : 0,
            "60.000000" : 0,
            "70.000000" : 0,
            "80.000000" : 0,
            "90.000000" : 0,
            "95.000000" : 0,
            "99.000000" : 0,
            "99.500000" : 0,
            "99.900000" : 0,
            "99.950000" : 0,
            "99.990000" : 0
          }
        },
        "lat_ns" : {
          "min" : 0,
          "max" : 0,
          "mean" : 0.000000,
          "stddev" : 0.000000
        },
        "bw_min" : 0,
        "bw_max" : 0,
        "bw_agg" : 0.000000,
        "bw_mean" : 0.000000,
        "bw_dev" : 0.000000,
        "bw_samples" : 0,
        "iops_min" : 0,
        "iops_max" : 0,
        "iops_mean" : 0.000000,
        "iops_stddev" : 0.000000,
        "iops_samples" : 0
      },
      "sync" : {
        "lat_ns" : {
          "min" : 0,
          "max" : 0,
          "mean" : 0.000000,
          "stddev" : 0.000000,
          "percentile" : {
            "1.000000" : 0,
            "5.000000" : 0,
            "10.000000" : 0,
            "20.000000" : 0,
            "30.000000" : 0,
            "40.000000" : 0,
            "50.000000" : 0,
            "60.000000" : 0,
            "70.000000" : 0,
            "80.000000" : 0,
            "90.000000" : 0,
            "95.000000" : 0,
            "99.000000" : 0,
            "99.500000" : 0,
            "99.900000" : 0,
            "99.950000" : 0,
            "99.990000" : 0
          }
        },
        "total_ios" : 0
      },
      "job_runtime" : 30002,
      "usr_cpu" : 3.589761,
      "sys_cpu" : 13.155790,
      "ctx" : 290049,
      "majf" : 0,
      "minf" : 1033,
      "iodepth_level" : {
        "1" : 0.100000,
        "2" : 0.100000,
        "4" : 0.100000,
        "8" : 0.100000,
        "16" : 0.100000,
        "32" : 99.992369,
        ">=64" : 0.000000
      },
      "iodepth_submit" : {
        "0" : 0.000000,
        "4" : 100.000000,
        "8" : 0.000000,
        "16" : 0.000000,
        "32" : 0.000000,
        "64" : 0.000000,
        ">=64" : 0.000000
      },
      "iodepth_complete" : {
        "0" : 0.000000,
        "4" : 99.999754,
        "8" : 0.000000,
        "16" : 0.000000,
        "32" : 0.100000,
        "64" : 0.000000,
        ">=64" : 0.000000
      },
      "latency_ns" : {
        "2" : 0.000000,
        "4" : 0.000000,
        "10" : 0.000000,
        "20" : 0.000000,
        "50" : 0.000000,
        "100" : 0.000000,
        "250" : 0.000000,
        "500" : 0.000000,
        "750" : 0.000000,
        "1000" : 0.000000
      },
      "latency_us" : {
        "2" : 0.000000,
        "4" : 0.000000,
        "10" : 0.000000,
        "20" : 0.000000,
        "50" : 0.000000,
        "100" : 0.000000,
        "250" : 0.010000,
        "500" : 0.000000,
        "750" : 0.010000,
        "1000" : 0.010000
      },
      "latency_ms" : {
        "2" : 12.108964,
        "4" : 87.858544,
        "10" : 0.022153,
        "20" : 0.010000,
        "50" : 0.000000,
        "100" : 0.000000,
        "250" : 0.000000,
        "500" : 0.000000,
        "750" : 0.000000,
        "1000" : 0.000000,
        "2000" : 0.000000,
        ">=2000" : 0.000000
      },
      "latency_depth" : 32,
      "latency_target" : 0,
      "latency_percentile" : 100.000000,
      "latency_window" : 0
    }
  ],
  "disk_util" : [
    {
      "name" : "vdb",
      "read_ios" : 404891,
      "write_ios" : 0,
      "read_merges" : 0,
      "write_merges" : 0,
      "read_ticks" : 951572,
      "write_ticks" : 0,
      "in_queue" : 917220,
      "util" : 99.683196
    }
  ]
}
